ansiscaf/__init__.py
ansiscaf/ansiscaf.py
ansiscaf-0.0.3.dist-info/DESCRIPTION.rst
ansiscaf-0.0.3.dist-info/METADATA
ansiscaf-0.0.3.dist-info/RECORD
ansiscaf-0.0.3.dist-info/WHEEL
ansiscaf-0.0.3.dist-info/entry_points.txt
ansiscaf-0.0.3.dist-info/metadata.json
ansiscaf-0.0.3.dist-info/top_level.txt
