Metadata-Version: 2.0
Name: ansiscaf
Version: 0.0.3
Summary: ansible scaffold
Home-page: https://github.com/terryshi96/ansiscaf
Author: terry.shi
Author-email: terryshi96@yahoo.com
License: MIT License
Keywords: ansible scaffold
Platform: UNKNOWN
